sklik/__init__.py
sklik/api.py
sklik/exception.py
sklik/object.py
sklik/report.py
sklik/util.py
sklik-1.0.6.dist-info/METADATA
sklik-1.0.6.dist-info/WHEEL
sklik-1.0.6.dist-info/RECORD
