Metadata-Version: 2.4
Name: sklik
Version: 1.0.6
Summary: Python Sklik API (unofficial)
Author-email: Peter Pleško <peter.plesko@gmail.com>
License-Expression: MIT
Keywords: report,sklik
Requires-Python: ~=3.9
Requires-Dist: pendulum>=3.0.0
Requires-Dist: pydantic<3,>=2.5.2
Requires-Dist: requests<3,>=2.31.0
